{
    "_b": [
        true,
        {
            "book": 24,
            "start_chapter": 1,
            "start_verse": 1,
            "end_chapter": 52,
            "end_verse": 34,
            "end_book": null
        }
    ],
    "book": 24,
    "version": "ASV",
    "verses": [
        {
            "verse_id": 24027001,
            "text": "\u00b6 In the beginning of the reign of <i>[a]</i>Jehoiakim the son of Josiah, king of Judah, came this word unto Jeremiah from Jehovah, saying, ",
            "version": "ASV",
            "clsstr": "Jer-27-1",
            "footnotes": [
                {
                    "a": "Properly <i>Zedekiah</i>. See verses [[3]], [[12]], [[20]]; [[28:1]]"
                }
            ],
            "crossrefs": []
        },
        {
            "verse_id": 24027002,
            "text": "Thus saith Jehovah to me: Make thee bonds and bars, and put them upon thy neck; ",
            "version": "ASV",
            "clsstr": "Jer-27-2",
            "footnotes": [],
            "crossrefs": []
        },
        {
            "verse_id": 24027003,
            "text": "and send them to the king of Edom, and to the king of Moab, and to the king of the children of Ammon, and to the king of Tyre, and to the king of Sidon, by the hand of the messengers that come to Jerusalem unto Zedekiah king of Judah: ",
            "version": "ASV",
            "clsstr": "Jer-27-3",
            "footnotes": [],
            "crossrefs": []
        },
        {
            "verse_id": 24027004,
            "text": "and give them a charge unto their masters, saying, Thus saith Jehovah of hosts, the God of Israel, Thus shall ye say unto your masters: ",
            "version": "ASV",
            "clsstr": "Jer-27-4",
            "footnotes": [],
            "crossrefs": []
        },
        {
            "verse_id": 24027005,
            "text": "I have made the earth, the men and the beasts that are upon the face of the earth, by my great power and by my outstretched arm; and I give it unto whom it seemeth right unto me. ",
            "version": "ASV",
            "clsstr": "Jer-27-5",
            "footnotes": [],
            "crossrefs": []
        },
        {
            "verse_id": 24027006,
            "text": "And now have I given all these lands into the hand of Nebuchadnezzar the king of Babylon, my servant; and the beasts of the field also have I given him to serve him. ",
            "version": "ASV",
            "clsstr": "Jer-27-6",
            "footnotes": [],
            "crossrefs": []
        },
        {
            "verse_id": 24027007,
            "text": "And all the nations shall serve him, and his son, and his son\u2019s son, until the time of his own land come: and then many nations and great kings shall make him their bondman. ",
            "version": "ASV",
            "clsstr": "Jer-27-7",
            "footnotes": [],
            "crossrefs": []
        },
        {
            "verse_id": 24027008,
            "text": "And it shall come to pass, that the nation and the kingdom which will not serve the same Nebuchadnezzar king of Babylon, and that will not put their neck under the yoke of the king of Babylon, that nation will I punish, saith Jehovah, with the sword, and with the famine, and with the pestilence, until I have consumed them by his hand. ",
            "version": "ASV",
            "clsstr": "Jer-27-8",
            "footnotes": [],
            "crossrefs": []
        },
        {
            "verse_id": 24027009,
            "text": "But as for you, hearken ye not to your prophets, nor to your diviners, nor to your dreams, nor to your soothsayers, nor to your sorcerers, that speak unto you, saying, Ye shall not serve the king of Babylon: ",
            "version": "ASV",
            "clsstr": "Jer-27-9",
            "footnotes": [],
            "crossrefs": []
        },
        {
            "verse_id": 24027010,
            "text": "for they prophesy a lie unto you, to remove you far from your land, and that I should drive you out, and ye should perish. ",
            "version": "ASV",
            "clsstr": "Jer-27-10",
            "footnotes": [],
            "crossrefs": []
        },
        {
            "verse_id": 24027011,
            "text": "But the nation that shall bring their neck under the yoke of the king of Babylon, and serve him, that  will I let remain in their own land, saith Jehovah; and they shall till it, and dwell therein.",
            "version": "ASV",
            "clsstr": "Jer-27-11",
            "footnotes": [],
            "crossrefs": []
        },
        {
            "verse_id": 24027012,
            "text": "\u00b6 And I spake to Zedekiah king of Judah according to all these words, saying, Bring your necks under the yoke of the king of Babylon, and serve him and his people, and live. ",
            "version": "ASV",
            "clsstr": "Jer-27-12",
            "footnotes": [],
            "crossrefs": []
        },
        {
            "verse_id": 24027013,
            "text": "Why will ye die, thou and thy people, by the sword, by the famine, and by the pestilence, as Jehovah hath spoken concerning the nation that will not serve the king of Babylon? ",
            "version": "ASV",
            "clsstr": "Jer-27-13",
            "footnotes": [],
            "crossrefs": []
        },
        {
            "verse_id": 24027014,
            "text": "And hearken not unto the words of the prophets that speak unto you, saying, Ye shall not serve the king of Babylon; for they prophesy a lie unto you. ",
            "version": "ASV",
            "clsstr": "Jer-27-14",
            "footnotes": [],
            "crossrefs": []
        },
        {
            "verse_id": 24027015,
            "text": "For I have not sent them, saith Jehovah, but they prophesy falsely in my name; that I may drive you out, and that ye may perish, ye, and the prophets that prophesy unto you.",
            "version": "ASV",
            "clsstr": "Jer-27-15",
            "footnotes": [],
            "crossrefs": []
        },
        {
            "verse_id": 24027016,
            "text": "\u00b6 Also I spake to the priests and to all this people, saying, Thus saith Jehovah: Hearken not to the words of your prophets that prophesy unto you, saying, Behold, the vessels of Jehovah\u2019s house shall now shortly be brought again from Babylon; for they prophesy a lie unto you. ",
            "version": "ASV",
            "clsstr": "Jer-27-16",
            "footnotes": [],
            "crossrefs": []
        },
        {
            "verse_id": 24027017,
            "text": "Hearken not unto them; serve the king of Babylon, and live: wherefore should this city become a desolation? ",
            "version": "ASV",
            "clsstr": "Jer-27-17",
            "footnotes": [],
            "crossrefs": []
        },
        {
            "verse_id": 24027018,
            "text": "But if they be prophets, and if the word of Jehovah be with them, let them now make intercession to Jehovah of hosts, that the vessels which are left in the house of Jehovah, and in the house of the king of Judah, and at Jerusalem, go not to Babylon. ",
            "version": "ASV",
            "clsstr": "Jer-27-18",
            "footnotes": [],
            "crossrefs": []
        },
        {
            "verse_id": 24027019,
            "text": "For thus saith Jehovah of hosts concerning the pillars, and concerning the sea, and concerning the bases, and concerning the residue of the vessels that are left in this city, ",
            "version": "ASV",
            "clsstr": "Jer-27-19",
            "footnotes": [],
            "crossrefs": []
        },
        {
            "verse_id": 24027020,
            "text": "which Nebuchadnezzar king of Babylon took not, when he carried away captive Jeconiah the son of Jehoiakim, king of Judah, from Jerusalem to Babylon, and all the nobles of Judah and Jerusalem; ",
            "version": "ASV",
            "clsstr": "Jer-27-20",
            "footnotes": [],
            "crossrefs": []
        },
        {
            "verse_id": 24027021,
            "text": "yea, thus saith Jehovah of hosts, the God of Israel, concerning the vessels that are left in the house of Jehovah, and in the house of the king of Judah, and at Jerusalem: ",
            "version": "ASV",
            "clsstr": "Jer-27-21",
            "footnotes": [],
            "crossrefs": []
        },
        {
            "verse_id": 24027022,
            "text": "They shall be carried to Babylon, and there shall they be, until the day that I visit them, saith Jehovah; then will I bring them up, and restore them to this place.",
            "version": "ASV",
            "clsstr": "Jer-27-22",
            "footnotes": [],
            "crossrefs": []
        }
    ],
    "short_title": "Jeremiah",
    "chapters": 27
}